{
  "main": {
    "id": "1e90597da170e377",
    "type": "split",
    "children": [
      {
        "id": "11e1856c637787e4",
        "type": "tabs",
        "children": [
          {
            "id": "a24c95c0079b1305",
            "type": "leaf",
            "state": {
              "type": "markdown",
              "state": {
                "file": "Quest Settings/Village of the Damned/Felicity Mills - Overview.md",
                "mode": "source",
                "source": false
              }
            }
          }
        ]
      }
    ],
    "direction": "vertical"
  },
  "left": {
    "id": "41623870835e5200",
    "type": "split",
    "children": [
      {
        "id": "f197464f461aaad4",
        "type": "tabs",
        "children": [
          {
            "id": "649a31624618a087",
            "type": "leaf",
            "state": {
              "type": "file-explorer",
              "state": {
                "sortOrder": "alphabetical"
              }
            }
          },
          {
            "id": "a63053d21eadc874",
            "type": "leaf",
            "state": {
              "type": "search",
              "state": {
                "query": "",
                "matchingCase": false,
                "explainSearch": false,
                "collapseAll": false,
                "extraContext": false,
                "sortOrder": "alphabetical"
              }
            }
          },
          {
            "id": "9e56554e4279bce3",
            "type": "leaf",
            "state": {
              "type": "starred",
              "state": {}
            }
          }
        ]
      }
    ],
    "direction": "horizontal",
    "width": 300
  },
  "right": {
    "id": "ff207632623c35db",
    "type": "split",
    "children": [
      {
        "id": "20817a9587a63730",
        "type": "tabs",
        "children": [
          {
            "id": "dd9647cb227fb0d6",
            "type": "leaf",
            "state": {
              "type": "backlink",
              "state": {
                "file": "Quest Settings/Village of the Damned/Felicity Mills - Overview.md",
                "collapseAll": false,
                "extraContext": false,
                "sortOrder": "alphabetical",
                "showSearch": false,
                "searchQuery": "",
                "backlinkCollapsed": false,
                "unlinkedCollapsed": true
              }
            }
          },
          {
            "id": "fc6560271852fe6c",
            "type": "leaf",
            "state": {
              "type": "outgoing-link",
              "state": {
                "file": "Quest Settings/Village of the Damned/Felicity Mills - Overview.md",
                "linksCollapsed": false,
                "unlinkedCollapsed": true
              }
            }
          },
          {
            "id": "bc8d9b1300eb6f15",
            "type": "leaf",
            "state": {
              "type": "tag",
              "state": {
                "sortOrder": "frequency",
                "useHierarchy": false
              }
            }
          },
          {
            "id": "be3f1cd8b08e5d55",
            "type": "leaf",
            "state": {
              "type": "outline",
              "state": {
                "file": "Quest Settings/Village of the Damned/Felicity Mills - Overview.md"
              }
            }
          }
        ]
      }
    ],
    "direction": "horizontal",
    "width": 300
  },
  "left-ribbon": {
    "hiddenItems": {
      "switcher:Open quick switcher": false,
      "graph:Open graph view": false,
      "canvas:Create new canvas": false,
      "daily-notes:Open today's daily note": false,
      "templates:Insert template": false,
      "command-palette:Open command palette": false
    }
  },
  "active": "a24c95c0079b1305",
  "lastOpenFiles": [
    "Major Characters/Backstories/Rot_background.png",
    "Quest Settings/Village of the Damned/Felicity Mills - Overview.md",
    "Old Towne.md",
    "Items/Memory Gems.md",
    "Major Characters/Dementia Malidict.md",
    "Major Characters/Backstories/Chess's Downfall.md",
    "Misty Valley.md",
    "Plans/Dementia's Plans.md",
    "Original Memory Gem.md",
    "Princedom War.md",
    "Major Characters/Rot.md",
    "Quest Settings/Village of the Damned/Village NPCs",
    "Quest Settings",
    "Quest Settings/Village of the Damned",
    "2023-03-17.md",
    "Untitled.canvas",
    "Items/Talisman of Lost Thoughts.md",
    "Game-Notes",
    "Nature's Vengence.md",
    "Chess's.md",
    "[Chess's.md",
    "[[Chess's.md",
    "Rot_background.png",
    "Characters/Backstories/'s background.png",
    "Characters/Backstories/Rot.png",
    "[[Chess.md",
    "Chess.md",
    "Major Characters/Backstories",
    "Plans",
    "Major Characters",
    "Items"
  ]
}